{
  "$schema": "https://ui.shadcn.com/schema/registry-item.json",
  "name": "utils",
  "type": "registry:item",
  "files": [
    {
      "path": "lib/utils.ts",
      "content": "export function cn<TState = Record<string, unknown>>(\n  ...inputs: (\n    | string\n    | undefined\n    | null\n    | false\n    | (() => string)\n    | ((state: TState) => string)\n  )[]\n) {\n  return inputs.filter(Boolean).join(\" \");\n}\n",
      "type": "registry:file",
      "target": "~/lib/utils.ts"
    }
  ]
}